Metadata-Version: 2.1
Name: aiogram-calendar-rus
Version: 1.0
Summary: Russian version for aiogram-calendar
Home-page: UNKNOWN
Author-email: nikita.efan.2017@gmail.com
License: UNKNOWN
Platform: UNKNOWN
